{
  "userId": "Nh8RiZnweFcNKZ9Nx5nDwvNSU4d2",
  "documents": [
    {
      "pageContent": "KalSarpa Dosha Analysis:\n            Type: N/A\n            Present: No\n            ",
      "metadata": {
        "userId": "Nh8RiZnweFcNKZ9Nx5nDwvNSU4d2",
        "chartType": "kalsarpa_details",
        "timestamp": "2025-08-20T16:59:55.932Z"
      }
    },
    {
      "pageContent": "Astrological Details:\n          Sign: Taurus\n          Ascendant: Aquarius\n          Ascendant Lord: Saturn\n          Nakshatra: Rohini\n          Nakshatra Lord: Moon\n          Charan: 1\n          Yog: Vishkumbha\n          Karan: Gara\n          Tithi: Shukla-Saptami\n          Tatva: Earth\n          Varna: Vaishya\n          Vashya: Chatuspad\n          Yoni: Sarp\n          Gan: Manushya\n          Nadi: Ant\n          Sign Lord: Venus\n          Name Alphabet: O\n          Paya: Iron",
      "metadata": {
        "userId": "Nh8RiZnweFcNKZ9Nx5nDwvNSU4d2",
        "chartType": "astro_details",
        "timestamp": "2025-08-20T16:59:55.924Z",
        "sign": "Taurus",
        "ascendant": "Aquarius",
        "nakshatra": "Rohini"
      }
    }
  ],
  "timestamp": "2025-08-20T16:59:58.754Z"
}